pyredisrpc/__init__.py
pyredisrpc/pyredisrpc.py
pyredisrpc-0.4.0.dist-info/METADATA
pyredisrpc-0.4.0.dist-info/WHEEL
pyredisrpc-0.4.0.dist-info/top_level.txt
pyredisrpc-0.4.0.dist-info/RECORD
