Metadata-Version: 2.1
Name: pyredisrpc
Version: 0.4.0
Summary: rpc over redis for python
Home-page: https://github.com/gowhari/pyredisrpc
Author: Iman Gowhari
Author-email: gowhari@gmail.com
License: MIT
Platform: UNKNOWN
Requires-Dist: redis
